<?xml version="1.0" encoding="utf-8"?>
<tileset name="Hangables">
    <brush name="wall lamp" />
    <brush name="wall lamp - lit" />
    <brush name="wall torch" />
    <brush name="wall torch - lit" />
    <brush name="wall candle" />
    <brush name="wall candle - lit" />
    <brush name="bambu wall torch" />
    <brush name="bambu wall torch - lit" />
    <brush name="cage wall lamp" />
    <brush name="cage wall lamp - lit" />
    <brush name="walled candle" />
    <brush name="purple energy wall lamp" />
    <brush name="purple energy wall lamp - lit" />
    <brush name="blue energy wall lamp" />
    <brush name="blue energy wall lamp - lit" />
    <brush name="yalahar wall candle" />
    <brush name="yalahar wall candle - lit" />
    <brush name="dragon wall candle" />
    <brush name="dragon wall candle - lit" />
    <brush name="zao wall candle" />
    <brush name="zao wall candle - lit" />
    <brush name="skull torch" />
    <brush name="zao torch1" />
    <brush name="zao torch1 - lit" />
    <brush name="zao torch2" />
    <brush name="zao torch2 - lit" />
    <brush name="wall lamp2" />
    <brush name="wall lamp2 - lit" />
    <brush name="wall candle2" />
    <brush name="wall candle2 - lit" />
    <brush name="wall dual lamp" />
    <brush name="wall dual lamp - lit" />
			-- tapestry --
			<brush name="tapestry king" />
    <item id="1857" />
    <item id="1860" />
    <item id="1863" />
    <item id="1866" />
    <item id="1869" />
    <item id="1872" />
    <item id="1880" />
    <brush name="pirate flag" />
    <brush name="yalahar tapestry" />
    <brush name="torn yalahar tapestry" />
    <brush name="long yalahar tapestry (normal)" />
    <brush name="long yalahar tapestry (royal)1" />
    <brush name="long yalahar tapestry (royal)2" />
    <brush name="long yalahar tapestry (torn)" />
    <brush name="long yalahar tapestry (sides)" />
			-- banner --
			<item fromid="1819" toid="1824" />
    <brush name="banner1" />
    <brush name="banner2" />
    <brush name="banner3" />
    <brush name="banner4" />
    <brush name="banner5" />
    <brush name="banner6" />
    <brush name="banner7" />
    <brush name="banner8" />
    <brush name="banner9" />
    <brush name="banner10" />
    <brush name="banner11" />
    <brush name="banner12" />
    <brush name="banner13" />
    <brush name="banner14" />
    <brush name="zao banner" />
    <brush name="zao banner - dragon" />
    <brush name="orange black tapestry" />
    <brush name="orange black tapestry - swords" />
    <brush name="tattered banner1" />
    <brush name="tattered banner2" />
    <brush name="tattered banner3" />
    <brush name="tattered curtain" />
    <brush name="torn tattered curtain" />
    <brush name="hieroglyph banner" />
    <brush name="pharaoh banner" />
			-- nature --
			<brush name="hangable moss" />
    <brush name="dark hangable moss" />
    <brush name="burnt wall" />
    <brush name="animated bat" />
    <brush name="slime" />
    <brush name="water trinkle" />
    <brush name="hanging acid" />
    <brush name="flowery garland1" />
    <brush name="flowery garland2" />
    <brush name="flowery garland3" />
    <brush name="leaf wreath1" />
    <brush name="leaf wreath2" />
    <brush name="leaf wreath3" />
    <brush name="leaf wreath4" />
    <brush name="zao hangable1" />
    <brush name="zao hangable2" />
    <brush name="zao hangable3" />
    <brush name="zao gem1" />
    <brush name="zao gem2" />
    <brush name="zao gem3" />
    <brush name="zao crystal1" />
    <brush name="zao crystal2" />
    <brush name="zao crystal3" />
    <brush name="zao crystal4" />
    <brush name="zao crystal5" />
    <brush name="dark spikes (hangable)" />
    <brush name="colorful hanging honey" />
    <brush name="bland hanging honey" />
    <brush name="unknown hanging1" />
    <brush name="unknown hanging2" />
    <brush name="unknown hanging3" />
    <brush name="hanging slime fungus" />
    <brush name="bearded hedgehog moss" />
    <brush name="barnacles" />
    <brush name="swamp lichen" />
    <brush name="oramond sludge" />
    <brush name="oramond dripping sludge" />
    <brush name="blue sludge" />
    <brush name="unknown hanging4" />
    <brush name="unknown hanging5" />
    <brush name="unknown hanging6" />
    <brush name="unknown hanging7" />
    <brush name="unknown hanging8" />
    <brush name="unknown hanging9" />
    <brush name="unknown hanging10" />
    <brush name="transition unknown hanging 8 to 9" />
    <brush name="transition unknown hanging 9 to 8" />
    <brush name="transition unknown hanging 9 to 10" />
    <brush name="transition unknown hanging 10 to 9" />
    <brush name="transition unknown hanging 8 to 10" />
    <brush name="transition unknown hanging 10 to 8" />
			-- signs --
			<brush name="archer's shop sign" />
    <brush name="armor shop sign" />
    <brush name="weapon shop sign" />
    <brush name="tool shop sign" />
    <brush name="food shop sign" />
    <brush name="furniture shop sign" />
    <brush name="grape shop sign" />
    <brush name="banana shop sign" />
    <brush name="depot sign" />
    <brush name="post sign" />
    <brush name="gem shop sign" />
			-- trophies --
			<brush name="demon trophy" />
    <brush name="wolf trophy" />
    <brush name="orc trophy" />
    <brush name="behemoth trophy" />
    <brush name="deer trophy" />
    <brush name="cyclops trophy" />
    <brush name="dragon trophy" />
    <brush name="lion trophy" />
    <brush name="minotaur trophy" />
    <brush name="orc trophy2" />
    <brush name="fish trophy" />
    <brush name="strange trophy" />
    <brush name="trophy of obujos" />
    <brush name="trophy of tanjis" />
    <brush name="trophy of jaul" />
    <brush name="werebadger trophy" />
    <brush name="wereboar trophy" />
    <brush name="werewolf trophy" />
    <brush name="werebear trophy" />
			-- architectural --
			<brush name="palisade hangable" />
    <brush name="wooden dragon" />
    <brush name="wooden bull" />
    <brush name="wooden yeti" />
    <brush name="spikes" />
    <brush name="stone gargoyle1" />
    <brush name="stone gargoyle2" />
    <brush name="stone gargoyle3" />
    <brush name="stone gargoyle4" />
    <brush name="goddess statue" />
    <brush name="sun emblem" />
    <brush name="defensive construction1" />
    <brush name="defensive construction2" />
    <brush name="serpent construction1" />
    <brush name="serpent construction2" />
    <brush name="serpent construction3" />
    <brush name="serpent construction4" />
    <brush name="skull decoration" />
    <brush name="zaoan decoration1" />
    <brush name="zaoan decoration2" />
    <brush name="zaoan decoration3" />
    <brush name="zaoan decoration4" />
    <brush name="zao arch1" />
    <brush name="zao arch2" />
    <brush name="zao arch3" />
    <brush name="zao arch4" />
    <brush name="zao arch5" />
    <item id="12037" />
			-- rest --
			<item id="1877" />
    <item id="1881" />
    <item id="1845" />
    <item id="1848" />
    <item id="1851" />
    <brush name="wall mirror" />
    <brush name="vengoth wall mirror" />
    <brush name="broken vengoth wall mirror" />
    <brush name="mirror" />
    <item id="1852" />
    <item id="1853" />
    <item id="1854" />
    <brush name="large painting1" />
    <brush name="large painting2" />
    <brush name="large painting3" />
    <brush name="portrait" />
    <brush name="rafzan painting" />
    <brush name="large rafzan painting" />
    <brush name="pirate emblem" />
    <brush name="hanging swords" />
    <brush name="wall chain" />
    <brush name="hanging skull" />
    <brush name="hanging triple skull" />
    <brush name="cobra wall statue" />
    <brush name="head stone cobra" />
    <brush name="head stone cobra with fumes" />
    <brush name="large map" />
    <brush name="celestial map" />
    <brush name="chalk board" />
    <brush name="pinned note" />
    <brush name="balloons" />
    <brush name="shield and sword" />
    <brush name="shield1" />
    <brush name="shield2" />
    <brush name="shield3" />
    <brush name="shield4" />
    <brush name="shield5" />
    <brush name="shield6" />
    <brush name="shield7" />
    <brush name="feather decoration" />
    <brush name="white dried fur" />
    <brush name="brown dried fur" />
    <brush name="tiger fur" />
    <brush name="mammoth fur" />
    <brush name="fish" />
    <brush name="bat" />
    <brush name="wooden planks (hangable)" />
    <brush name="viking shield1" />
    <brush name="viking shield2" />
    <brush name="viking shield3" />
    <brush name="sacrophagus - closed" />
    <brush name="sacrophagus - open" />
    <brush name="skeleton niche (skeleton)" />
    <brush name="skeleton niche (niche)" />
    <brush name="small window" />
    <brush name="decorative spear" />
    <brush name="horn decoration (hanging)" />
    <brush name="iron case" />
    <brush name="deer antlers" />
    <brush name="wolf hide" />
    <brush name="hanging wolf" />
    <brush name="hanging deer" />
    <brush name="hanging fur" />
    <brush name="cutlery" />
    <brush name="ornate wall (hangable)" />
    <brush name="hanging cord" />
    <brush name="lampions" />
    <brush name="flitter" />
    <brush name="party snake" />
    <brush name="hanging drinks" />
    <brush name="royal emblems" />
    <brush name="short lampions" />
    <brush name="short flitter" />
    <brush name="short party snake" />
    <brush name="short emblems1" />
    <brush name="short emblems2" />
    <brush name="triangle flags - south" />
    <brush name="triangle flags - east" />
    <brush name="sun emblem cloth" />
    <brush name="red white flag" />
    <brush name="cave painting1" />
    <brush name="cave painting2" />
    <brush name="cave painting3" />
    <brush name="cave painting4" />
    <brush name="orange long glow" />
    <brush name="orange short glow" />
    <brush name="blue ornament" />
    <brush name="blue white drape" />
    <brush name="gold lion ornament" />
    <brush name="gold yakhal ornament" />
    <brush name="gold head ornament" />
    <brush name="gold head ornament - horns" />
    <brush name="gold railing ornament" />
    <brush name="gold handle ornament" />
    <brush name="gold window ornament" />
    <brush name="clay window ornament" />
    <brush name="venorean ornament1" />
    <brush name="venorean ornament2" />
    <brush name="venorean ornament3" />
    <brush name="venorean ornament4" />
    <brush name="oramond hangable - full" />
    <brush name="oramond hangable - empty" />
    <brush name="wanted note" />
    <brush name="red gem" />
    <brush name="green gem" />
    <brush name="purple gem" />
    <brush name="blue gem" />
    <brush name="gold wall ornament" />
    <brush name="scarab ornament" />
    <brush name="gold claw ornament" />
    <brush name="scorpion ornament" />
    <brush name="hieroglyphs" />
    <brush name="niche" />
    <brush name="carving of a scorpion" />
    <brush name="strange carving" />
    <brush name="carving of a battle" />
</tileset>
