<?xml version="1.0" encoding="utf-8"?>
<tileset name="Others">
    <item id="1397" />
    <item id="1548" />
    <item fromid="3223" toid="3224" />
    <item id="3310" />
    <item fromid="3506" toid="3507" />
    <item fromid="3523" toid="3524" />
    <item fromid="3711" toid="3714" />
    <item fromid="3745" toid="3765" />
    <item fromid="3768" toid="3791" />
    <item fromid="3861" toid="3881" />
    <item fromid="3896" toid="3900" />
    <item fromid="3943" toid="3950" />
    <item fromid="3954" toid="3956" />
    <item fromid="3958" toid="3959" />
    <item fromid="3963" toid="3964" />
    <item fromid="3976" toid="3980" />
    <item fromid="4838" toid="4840" />
    <item fromid="4845" toid="4846" />
    <item id="4849" />
    <item fromid="4857" toid="4859" />
    <item id="4861" />
    <item id="4873" />
    <item fromid="4992" toid="4994" />
    <item fromid="4996" toid="4997" />
    <item fromid="5014" toid="5024" />
    <item fromid="5057" toid="5060" />
    <item fromid="5463" toid="5467" />
    <item fromid="5469" toid="5477" />
    <item fromid="5480" toid="5484" />
    <item fromid="5504" toid="5514" />
    <item id="5521" />
    <item id="5539" />
    <item fromid="5544" toid="5553" />
    <item fromid="5555" toid="5564" />
    <item fromid="5596" toid="5597" />
    <item fromid="5614" toid="5624" />
    <item fromid="5655" toid="5659" />
    <item fromid="5669" toid="5670" />
    <item fromid="5675" toid="5676" />
    <item id="5687" />
    <item fromid="5691" toid="5692" />
    <item fromid="5704" toid="5705" />
    <item fromid="5707" toid="5709" />
    <item fromid="5732" toid="5740" />
    <item fromid="5745" toid="5749" />
    <item fromid="5812" toid="5814" />
    <item fromid="5938" toid="5939" />
    <item id="6106" />
    <item id="6108" />
    <item fromid="6121" toid="6122" />
    <item id="6138" />
    <item fromid="6153" toid="6159" />
    <item id="6172" />
    <item fromid="6285" toid="6287" />
    <item fromid="6291" toid="6299" />
    <item id="6353" />
    <item id="6390" />
    <item fromid="6434" toid="6435" />
    <item fromid="6491" toid="6499" />
    <item id="6501" />
    <item fromid="6503" toid="6505" />
    <item fromid="6512" toid="6519" />
    <item fromid="6523" toid="6527" />
    <item id="6532" />
    <item fromid="6534" toid="6540" />
    <item fromid="6556" toid="6558" />
    <item fromid="6561" toid="6565" />
    <item fromid="6575" toid="6576" />
    <item fromid="6750" toid="6760" />
    <item fromid="6793" toid="6794" />
    <item id="6869" />
    <item fromid="6886" toid="6890" />
    <item id="6925" />
    <item fromid="6951" toid="6960" />
    <item id="6966" />
    <item fromid="6968" toid="6971" />
    <item fromid="6974" toid="6980" />
    <item fromid="6984" toid="6985" />
    <item fromid="6987" toid="6998" />
    <item id="7053" />
    <item id="7059" />
    <item id="7106" />
    <item fromid="7108" toid="7109" />
    <item fromid="7137" toid="7139" />
    <item fromid="7143" toid="7144" />
    <item fromid="7171" toid="7178" />
    <item fromid="7183" toid="7186" />
    <item id="7189" />
    <item id="7200" />
    <item fromid="7213" toid="7255" />
    <item id="7259" />
    <item fromid="7261" toid="7271" />
    <item fromid="7273" toid="7280" />
    <item id="7286" />
    <item fromid="7289" toid="7290" />
    <item fromid="7303" toid="7313" />
    <item id="7349" />
    <item fromid="7359" toid="7362" />
    <item fromid="7393" toid="7401" />
    <item id="7409" />
    <item fromid="7439" toid="7440" />
    <item id="7443" />
    <item fromid="7474" toid="7527" />
    <item fromid="7558" toid="7565" />
    <item fromid="7567" toid="7584" />
    <item id="7587" />
    <item fromid="7632" toid="7633" />
    <item id="7673" />
    <item fromid="7697" toid="7699" />
    <item id="7701" />
    <item id="7706" />
    <item fromid="7711" toid="7719" />
    <item fromid="7728" toid="7729" />
    <item fromid="7732" toid="7736" />
    <item fromid="7759" toid="7762" />
    <item fromid="7827" toid="7832" />
    <item fromid="7920" toid="7923" />
    <item fromid="7932" toid="7933" />
    <item id="7938" />
    <item fromid="7940" toid="7942" />
    <item id="7956" />
    <item fromid="7963" toid="7965" />
    <item fromid="7977" toid="8020" />
    <item id="8029" />
    <item fromid="8046" toid="8047" />
    <item fromid="8058" toid="8059" />
    <item id="8062" />
    <item id="8072" />
    <item fromid="8075" toid="8078" />
    <item fromid="8109" toid="8112" />
    <item fromid="8121" toid="8132" />
    <item fromid="8135" toid="8138" />
    <item fromid="8168" toid="8170" />
    <item fromid="8174" toid="8176" />
    <item id="8182" />
    <item fromid="8186" toid="8187" />
    <item id="8190" />
    <item fromid="8201" toid="8203" />
    <item id="8205" />
    <item fromid="8210" toid="8213" />
    <item fromid="8241" toid="8258" />
    <item id="8260" />
    <item id="8268" />
    <item id="8275" />
    <item id="8278" />
    <item id="8287" />
    <item id="8292" />
    <item fromid="8294" toid="8306" />
    <item fromid="8309" toid="8310" />
    <item fromid="8313" toid="8314" />
    <item id="8323" />
    <item fromid="8361" toid="8364" />
    <item fromid="8366" toid="8369" />
    <item id="8371" />
    <item fromid="8380" toid="8387" />
    <item id="8459" />
    <item fromid="8472" toid="8474" />
    <item fromid="8526" toid="8537" />
    <item fromid="8567" toid="8577" />
    <item fromid="8580" toid="8590" />
    <item id="8593" />
    <item fromid="8595" toid="8596" />
    <item id="8600" />
    <item fromid="8603" toid="8604" />
    <item id="8614" />
    <item fromid="8617" toid="8624" />
    <item fromid="8627" toid="8631" />
    <item fromid="8641" toid="8695" />
    <item fromid="8698" toid="8720" />
    <item fromid="8722" toid="8723" />
    <item fromid="8740" toid="8751" />
    <item fromid="8760" toid="8761" />
    <item id="8764" />
    <item id="8766" />
    <item fromid="8768" toid="8769" />
    <item fromid="8781" toid="8784" />
    <item fromid="8824" toid="8833" />
    <item fromid="8860" toid="8864" />
    <item fromid="8894" toid="8899" />
    <item id="8945" />
    <item id="8959" />
    <item fromid="8970" toid="8975" />
    <item fromid="8986" toid="9001" />
    <item fromid="9005" toid="9007" />
    <item fromid="9013" toid="9020" />
    <item fromid="9073" toid="9078" />
    <item fromid="9081" toid="9083" />
    <item fromid="9107" toid="9117" />
    <item id="9134" />
    <item id="9141" />
    <item id="9191" />
    <item fromid="9331" toid="9334" />
    <item fromid="9341" toid="9352" />
    <item id="9369" />
    <item fromid="9417" toid="9422" />
    <item id="9448" />
    <item fromid="9521" toid="9522" />
    <item fromid="9561" toid="9568" />
    <item fromid="9586" toid="9587" />
    <item fromid="9624" toid="9625" />
    <item fromid="9632" toid="9636" />
    <item id="9653" />
    <item id="9655" />
    <item fromid="9661" toid="9668" />
    <item fromid="9674" toid="9680" />
    <item fromid="9686" toid="9713" />
    <item fromid="9727" toid="9750" />
    <item fromid="9753" toid="9758" />
    <item id="9767" />
    <item fromid="9772" toid="9773" />
    <item id="9934" />
    <item fromid="9939" toid="9940" />
    <item fromid="9943" toid="9947" />
    <item fromid="9950" toid="9952" />
    <item id="9955" />
    <item fromid="9969" toid="9971" />
    <item id="9974" />
    <item id="9980" />
    <item fromid="9992" toid="10001" />
    <item id="10006" />
    <item id="10010" />
    <item fromid="10013" toid="10017" />
    <item fromid="10020" toid="10022" />
    <item fromid="10029" toid="10030" />
    <item id="10032" />
    <item fromid="10034" toid="10035" />
    <item fromid="10038" toid="10043" />
    <item fromid="10062" toid="10064" />
    <item id="10066" />
    <item fromid="10091" toid="10092" />
    <item id="10106" />
    <item id="10109" />
    <item fromid="10111" toid="10113" />
    <item fromid="10116" toid="10119" />
    <item fromid="10124" toid="10132" />
    <item id="10143" />
    <item fromid="10150" toid="10153" />
    <item fromid="10156" toid="10159" />
    <item id="10165" />
    <item id="10167" />
    <item id="10169" />
    <item id="10173" />
    <item fromid="10177" toid="10207" />
    <item fromid="10209" toid="10217" />
    <item fromid="10219" toid="10224" />
    <item fromid="10226" toid="10261" />
    <item fromid="10264" toid="10285" />
    <item fromid="10289" toid="10304" />
    <item id="10306" />
    <item fromid="10308" toid="10310" />
    <item id="10313" />
    <item id="10316" />
    <item fromid="10318" toid="10323" />
    <item fromid="10325" toid="10340" />
    <item fromid="10344" toid="10346" />
    <item fromid="10349" toid="10356" />
    <item fromid="10365" toid="10372" />
    <item id="10383" />
    <item id="10393" />
    <item fromid="10398" toid="10448" />
    <item fromid="10454" toid="10500" />
    <item fromid="10502" toid="10503" />
    <item fromid="10510" toid="10516" />
    <item fromid="10518" toid="10527" />
    <item fromid="10529" toid="10535" />
    <item fromid="10541" toid="10543" />
    <item fromid="10548" toid="10585" />
    <item fromid="10601" toid="10603" />
    <item fromid="10605" toid="10611" />
    <item fromid="10613" toid="10616" />
    <item id="10728" />
    <item id="10732" />
    <item fromid="10734" toid="10736" />
    <item fromid="10741" toid="10743" />
    <item id="10757" />
    <item fromid="10761" toid="10764" />
    <item fromid="10775" toid="10777" />
    <item fromid="10780" toid="10786" />
    <item fromid="10789" toid="10793" />
    <item id="10803" />
    <item fromid="10806" toid="10809" />
    <item id="10811" />
    <item id="10813" />
    <item fromid="10816" toid="10817" />
    <item fromid="10913" toid="10916" />
    <item fromid="10942" toid="10953" />
    <item fromid="10971" toid="10974" />
    <item fromid="10999" toid="11002" />
    <item fromid="11043" toid="11050" />
    <item fromid="11062" toid="11063" />
    <item fromid="11098" toid="11100" />
    <item fromid="11107" toid="11110" />
    <item id="11113" />
    <item fromid="11115" toid="11119" />
    <item id="11123" />
    <item fromid="11129" toid="11132" />
    <item id="11134" />
    <item id="11136" />
    <item fromid="11138" toid="11141" />
    <item id="11144" />
    <item fromid="11189" toid="11200" />
    <item fromid="11203" toid="11204" />
    <item fromid="11206" toid="11238" />
    <item fromid="11240" toid="11252" />
    <item fromid="11254" toid="11257" />
    <item fromid="11263" toid="11264" />
    <item fromid="11269" toid="11298" />
    <item fromid="11301" toid="11314" />
    <item fromid="11316" toid="11319" />
    <item fromid="11321" toid="11339" />
    <item fromid="11343" toid="11350" />
    <item fromid="11355" toid="11378" />
    <item fromid="11385" toid="11393" />
    <item fromid="11396" toid="11399" />
    <item fromid="11793" toid="11795" />
    <item id="11797" />
    <item fromid="12284" toid="12290" />
    <item id="12295" />
    <item id="12297" />
    <item id="12300" />
    <item fromid="12302" toid="12303" />
    <item id="12318" />
    <item id="12320" />
    <item fromid="12323" toid="12328" />
    <item id="12382" />
    <item fromid="12399" toid="12423" />
    <item fromid="12425" toid="12437" />
    <item fromid="12439" toid="12449" />
    <item fromid="12466" toid="12471" />
    <item fromid="12495" toid="12497" />
    <item fromid="12500" toid="12508" />
    <item fromid="12527" toid="12528" />
    <item fromid="12538" toid="12544" />
    <item fromid="12559" toid="12617" />
    <item fromid="12622" toid="12640" />
    <item fromid="12642" toid="12647" />
    <item id="12649" />
    <item id="12651" />
    <item fromid="12655" toid="12660" />
    <item id="13247" />
    <item fromid="13291" toid="13295" />
    <item id="13298" />
    <item id="13305" />
    <item fromid="13307" toid="13325" />
    <item fromid="13327" toid="13331" />
    <item id="13336" />
    <item fromid="13483" toid="13494" />
    <item id="13498" />
    <item fromid="13501" toid="13504" />
    <item id="13506" />
    <item fromid="13508" toid="13528" />
    <item fromid="13535" toid="13539" />
    <item id="13584" />
    <item fromid="13594" toid="13596" />
    <item fromid="13752" toid="13755" />
    <item fromid="13859" toid="13862" />
    <item fromid="13938" toid="13939" />
    <item id="13941" />
    <item fromid="20001" toid="20007" />
    <item fromid="20010" toid="20011" />
    <item fromid="20013" toid="20015" />
    <item id="20019" />
    <item id="20021" />
    <item fromid="20026" toid="20028" />
</tileset>
